dmc/__init__.py
gym_dmc/__init__.py
gym_dmc/dmc_env.py
gym_dmc/registry.py
gym_dmc/wrappers.py
gym_dmc/gym/__init__.py
gym_dmc/gym/core.py
gym_dmc/gym/spaces/__init__.py
gym_dmc/gym/spaces/box.py
gym_dmc/gym/spaces/dict.py
gym_dmc/gym/spaces/discrete.py
gym_dmc/gym/spaces/multi_binary.py
gym_dmc/gym/spaces/multi_discrete.py
gym_dmc/gym/spaces/space.py
gym_dmc/gym/spaces/tuple.py
gym_dmc/gym/spaces/utils.py
gym_dmc/gym/utils/__init__.py
gym_dmc/gym/utils/colorize.py
gym_dmc/gym/utils/ezpickle.py
gym_dmc/gym/utils/seeding.py
gym_dmc/wrappers/__init__.py
gym_dmc/wrappers/flat.py
gym_dmc/wrappers/order_enforcing.py
gym_dmc/wrappers/time_limit.py
specs/__init__.py
specs/test_gym_dmc.py
gym_dmc-0.3.0.dist-info/LICENSE
gym_dmc-0.3.0.dist-info/METADATA
gym_dmc-0.3.0.dist-info/WHEEL
gym_dmc-0.3.0.dist-info/top_level.txt
gym_dmc-0.3.0.dist-info/RECORD
