Metadata-Version: 2.1
Name: gym-dmc
Version: 0.3.0
Summary: gym-dmc is a gym wrapper around DeepMind Control Suite domains.
Home-page: https://github.com/geyang/gym-dmc
Author: Ge Yang<ge.ike.yang@gmail.com>
Author-email: ge.ike.yang@gmail.com
License-File: LICENSE
Requires-Dist: dm-control
Requires-Dist: numpy
